geometry_library/__init__.py
geometry_library/geometry.py
geometry_library-0.1.0.dist-info/LICENSE
geometry_library-0.1.0.dist-info/METADATA
geometry_library-0.1.0.dist-info/WHEEL
geometry_library-0.1.0.dist-info/top_level.txt
geometry_library-0.1.0.dist-info/RECORD
