Metadata-Version: 2.1
Name: geometry_library
Version: 0.1.0
Summary: A simple Python library for 2D geometry.
Home-page: https://github.com/Dada09898/Ankit_kumar_singh-geometry-library
Author: Ankit kumar singh
Author-email: singhkumar50866@gmail.com
License: MIT
Classifier: Development Status :: 3 - Alpha
Classifier: Intended Audience :: Developers
Classifier: License :: OSI Approved :: MIT License
Classifier: Programming Language :: Python :: 3
Classifier: Programming Language :: Python :: 3.7
Classifier: Programming Language :: Python :: 3.8
Classifier: Programming Language :: Python :: 3.9
Classifier: Programming Language :: Python :: 3.10
Classifier: Programming Language :: Python :: 3.11
Classifier: Operating System :: OS Independent
Requires-Python: >=3.7
License-File: LICENSE
